LICENSE.md
MANIFEST.in
README.md
requirements.txt
setup.py
me/__init__.py
me/aggregate.py
me/cli.py
me/healthkit.py
me/omnifocus.py
me/spreadsheet.py
me.csv.egg-info/PKG-INFO
me.csv.egg-info/SOURCES.txt
me.csv.egg-info/dependency_links.txt
me.csv.egg-info/entry_points.txt
me.csv.egg-info/requires.txt
me.csv.egg-info/top_level.txt
me.csv.egg-info/zip-safe