Metadata-Version: 1.0
Name: me.csv
Version: 0.0.1.dev0
Summary: Aggregate time and health tracking data
Home-page: https://github.com/ChrisCummins/me.csv
Author: Chris Cummins
Author-email: chrisc.101@gmail.com
License: MIT License
Platform: UNKNOWN
